chatbotpackage/__init__.py
chatbotpackage/admin.py
chatbotpackage/app.yaml
chatbotpackage/appengine_config.py
chatbotpackage/config.ini
chatbotpackage/get-pip.py
chatbotpackage/main.py
chatbotpackage/server.ini
chatbotpackage/certificates/__init__.py
chatbotpackage/certificates/cert.pem
chatbotpackage/certificates/key.pem
chatbotpackage/certificates/server.crt
chatbotpackage/certificates/server.csr
chatbotpackage/certificates/server.key
chatbotpackage/certificates/server.key.org
chatbotpackage/certificates/server.pem
chatbotpackage/chatbot/HelpDoc.txt
chatbotpackage/chatbot/__init__.py
chatbotpackage/chatbot/config.ini
chatbotpackage/chatbot/gui_chatbot.py
chatbotpackage/chatbot/train_chatbot.py
chatbotpackage/chatbot/training.ini
chatbotpackage/chatbot/__pycache__/admin.cpython-38.pyc
chatbotpackage/chatbot/__pycache__/gui_chatbot.cpython-38.pyc
chatbotpackage/chatbot/__pycache__/train_chatbot.cpython-38.pyc
chatbotpackage/chatbot/classes/classes_banks.pkl
chatbotpackage/chatbot/classes/classes_general.pkl
chatbotpackage/chatbot/classes/classes_healthcare.pkl
chatbotpackage/chatbot/intents/intents_banks.json
chatbotpackage/chatbot/intents/intents_general.json
chatbotpackage/chatbot/intents/intents_healthcare.json
chatbotpackage/chatbot/models/chatbot_model_bank.h5
chatbotpackage/chatbot/models/chatbot_model_general.h5
chatbotpackage/chatbot/models/chatbot_model_healthcare.h5
chatbotpackage/chatbot/server_config/server_bank.ini
chatbotpackage/chatbot/server_config/server_healthcare.ini
chatbotpackage/chatbot/words/words_banks.pkl
chatbotpackage/chatbot/words/words_general.pkl
chatbotpackage/chatbot/words/words_healthcare.pkl
chatbotpackage/lib/__init__.py
chatbotpackage/lib/bin/flask.exe
chatbotpackage/lib/click/__init__.py
chatbotpackage/lib/click/_bashcomplete.py
chatbotpackage/lib/click/_compat.py
chatbotpackage/lib/click/_termui_impl.py
chatbotpackage/lib/click/_textwrap.py
chatbotpackage/lib/click/_unicodefun.py
chatbotpackage/lib/click/_winconsole.py
chatbotpackage-0.14.dist-info/LICENSE
chatbotpackage-0.14.dist-info/METADATA
chatbotpackage-0.14.dist-info/WHEEL
chatbotpackage-0.14.dist-info/top_level.txt
chatbotpackage/lib/Flask-1.1.2.dist-info/INSTALLER
chatbotpackage/lib/Flask-1.1.2.dist-info/LICENSE.rst
chatbotpackage/lib/Flask-1.1.2.dist-info/METADATA
chatbotpackage/lib/Flask-1.1.2.dist-info/RECORD
chatbotpackage/lib/Flask-1.1.2.dist-info/REQUESTED
chatbotpackage/lib/Flask-1.1.2.dist-info/WHEEL
chatbotpackage/lib/Flask-1.1.2.dist-info/entry_points.txt
chatbotpackage/lib/Flask-1.1.2.dist-info/top_level.txt
chatbotpackage/lib/Jinja2-2.11.2.dist-info/INSTALLER
chatbotpackage/lib/Jinja2-2.11.2.dist-info/LICENSE.rst
chatbotpackage/lib/Jinja2-2.11.2.dist-info/METADATA
chatbotpackage/lib/Jinja2-2.11.2.dist-info/RECORD
chatbotpackage/lib/Jinja2-2.11.2.dist-info/WHEEL
chatbotpackage/lib/Jinja2-2.11.2.dist-info/entry_points.txt
chatbotpackage/lib/Jinja2-2.11.2.dist-info/top_level.txt
chatbotpackage/lib/MarkupSafe-1.1.1.dist-info/INSTALLER
chatbotpackage/lib/MarkupSafe-1.1.1.dist-info/LICENSE.rst
chatbotpackage/lib/MarkupSafe-1.1.1.dist-info/METADATA
chatbotpackage/lib/MarkupSafe-1.1.1.dist-info/RECORD
chatbotpackage/lib/MarkupSafe-1.1.1.dist-info/WHEEL
chatbotpackage/lib/MarkupSafe-1.1.1.dist-info/top_level.txt
chatbotpackage/lib/Werkzeug-1.0.1.dist-info/INSTALLER
chatbotpackage/lib/Werkzeug-1.0.1.dist-info/LICENSE.rst
chatbotpackage/lib/Werkzeug-1.0.1.dist-info/METADATA
chatbotpackage/lib/Werkzeug-1.0.1.dist-info/RECORD
chatbotpackage/lib/Werkzeug-1.0.1.dist-info/REQUESTED
chatbotpackage/lib/Werkzeug-1.0.1.dist-info/WHEEL
chatbotpackage/lib/Werkzeug-1.0.1.dist-info/top_level.txt
chatbotpackage/lib/click-7.1.2.dist-info/INSTALLER
chatbotpackage/lib/click-7.1.2.dist-info/LICENSE.rst
chatbotpackage/lib/click-7.1.2.dist-info/METADATA
chatbotpackage/lib/click-7.1.2.dist-info/RECORD
chatbotpackage/lib/click-7.1.2.dist-info/WHEEL
chatbotpackage/lib/click-7.1.2.dist-info/top_level.txt
chatbotpackage/lib/itsdangerous-1.1.0.dist-info/INSTALLER
chatbotpackage/lib/itsdangerous-1.1.0.dist-info/LICENSE.rst
chatbotpackage/lib/itsdangerous-1.1.0.dist-info/METADATA
chatbotpackage/lib/itsdangerous-1.1.0.dist-info/RECORD
chatbotpackage/lib/itsdangerous-1.1.0.dist-info/WHEEL
chatbotpackage/lib/itsdangerous-1.1.0.dist-info/top_level.txt
chatbotpackage-0.14.dist-info/RECORD
